{
  "$schema": "https://schema.management.azure.com/schemas/2019-04-01/deploymentParameters.json#",
  "contentVersion": "1.0.0.0",
  "parameters": {
    "existingAiFoundryName": {
      "value": "aifaiagt04"
    },
    "existingAISearchAccountName": {
      "value": "srchaiagt04"
    },
    "existingCosmosDbAccountName": {
      "value": "cosmosaiagt04"
    },
    "existingStorageAccountName": {
      "value": "staiagt04<randomstring>"
    },
    "existingBingAccountName": {
      "value": "bing-grounding"
    },
    "existingWebApplicationInsightsResourceName": {
      "value": "appi-aiagt04"
    }
  }
} 